{"questionId":"9076119","questionHtml":"<p>Determine the magnitude of the average resultant force acting on the block between B and C.</p>","markschemeHtml":"<p>use of impulse <em>F</em><sub>ave</sub> × Δ<em>t</em> =&nbsp;Δ<em>p</em></p>\n<p><strong><em>OR</em></strong></p>\n<p>use of <em>F</em> = <em>ma</em> with average acceleration</p>\n<p><strong><em>OR</em></strong></p>\n<p><em>F</em> =&nbsp;<span class=\"mjpage\"><math xmlns=\"http://www.w3.org/1998/Math/MathML\" alttext=\"\\frac{{80.0 \\times 34.3}}{{0.759}}\">\n  <mfrac>\n    <mrow>\n      <mn>80.0</mn>\n      <mo>×</mo>\n      <mn>34.3</mn>\n    </mrow>\n    <mrow>\n      <mn>0.759</mn>\n    </mrow>\n  </mfrac>\n</math></span></p>\n<p>&nbsp;</p>\n<p>3620<strong>«</strong>N<strong>»</strong></p>\n<p>&nbsp;</p>\n<p><em>Allow ECF from (a).</em></p>\n<p><strong><em>[2 marks]</em></strong></p>","meta":{"questionId":"9076119","referenceCode":"18M.2.HL.TZ1.1b.i","subjectId":"46-dp-physics-last-assessment-2024","title":"Determine the magnitude of the average resultant force acting on the block between B and C.","paper":"2","level":"HL","questionNumber":"b.i","marksAvailable":"[Maximum mark: 2]","breadcrumbLabels":["Core","Core","Topic 2: Mechanics","2.4 – Momentum and impulse","Core","Topic 2: Mechanics"],"memberSectionIds":[],"sectionOrders":{}}}