{"questionId":"1238251","questionHtml":"<p>Using the climograph, outline the pattern of rainfall.</p>","markschemeHtml":"<p>rainfall concentrated between April to December/peaks in June-August «followed by months with little/no rainfall» ✔</p>\n<p><em>OWTTE</em></p>","meta":{"questionId":"1238251","referenceCode":"19M.2.HL.TZ2.15a.iii","subjectId":"57-dp-biology-first-assessment-2025","title":"Using the climograph, outline the pattern of rainfall.","paper":"2","level":"HL","questionNumber":"a.iii","marksAvailable":"[Maximum mark: 1]","breadcrumbLabels":["D. Continuity and Change","D4.2 Stability and change","D4.2.14. Cyclical succession in ecosystems"],"memberSectionIds":[],"sectionOrders":{}},"schemaVersion":2}