{"questionId":"3022183","questionHtml":"<p>The micrograph shows a cross section of a lily (<em>Lilium longiflorum</em>) anther.</p>\n<p><img style=\"display:block;margin-left:auto;margin-right:auto;\" src=\"__IMG__/71d47c233c7e2271e0a7cf5171df672d168c8c70.png\" width=\"751\" height=\"460\"></p>\n<p style=\"text-align:center;\"><sup>[Source: Sinhyu / iStock.]</sup></p>\n<p>What can be found in X?<br><br></p>\n<p>A.&nbsp; Haploid nuclei produced by meiosis</p>\n<p>B.&nbsp; Diploid nuclei produced by fertilization</p>\n<p>C.&nbsp; Haploid nuclei produced by mitosis</p>\n<p>D.&nbsp; Diploid nuclei produced by pollination</p>","markschemeHtml":"<p>A</p>","meta":{"questionId":"3022183","referenceCode":"23M.1A.SL.TZ1.11","subjectId":"57-dp-biology-first-assessment-2025","title":"The micrograph shows a cross section of a lily (Lilium longiflorum) anther. [Source: Sinhyu / iStock.] What can be found in X? A. Haploid nuclei produced by meiosis B. Diploid nucl","paper":"1A","level":"SL","questionNumber":"11","marksAvailable":"[Maximum mark: 1]","breadcrumbLabels":["D. Continuity and Change","D2.1 Cell and nuclear division","D2.1.9. Meiosis as a reduction division"],"memberSectionIds":[],"sectionOrders":{}}}