{"questionId":"9065864","questionHtml":"<p>Structure IV contains a gland that secretes a sugary liquid. Suggest a benefit to the&nbsp;plant of secreting this liquid.</p>","markschemeHtml":"<ol style=\"list-style-type:lower-alpha;\">\n<li>attracts an insect/animal/which pollinates the flower;</li>\n<li>attracts a pollinator;</li>\n</ol>\n<p><em>Mpa: Both parts of the sentence are needed to award the point.</em></p>","meta":{"questionId":"9065864","referenceCode":"23M.2.SL.TZ2.3c","subjectId":"57-dp-biology-first-assessment-2025","title":"Structure IV contains a gland that secretes a sugary liquid. Suggest a benefit to the plant of secreting this liquid.","paper":"2","level":"SL","questionNumber":"c","marksAvailable":"[Maximum mark: 1]","breadcrumbLabels":["D. Continuity and Change","D3.1 Reproduction","D3.1.9. Features of an insect-pollinated flower"],"memberSectionIds":[],"sectionOrders":{}},"schemaVersion":2}