{"questionId":"9118753","questionHtml":"<p>Define the term <em>debt servicing</em> indicated in bold in <strong>Table 1</strong>.</p>","markschemeHtml":"<p><img src=\"__IMG__/a6d250998b7033f4e20cd4997a812f2b6148b5ea.png\"></p>","meta":{"questionId":"9118753","referenceCode":"22M.2.HL.TZ0.a.i","subjectId":"48-dp-economics","title":"Define the term debt servicing indicated in bold in Table 1.","paper":"2","level":"HL","questionNumber":"a.i","marksAvailable":"[Maximum mark: 2]","breadcrumbLabels":["First exams 2022","First exams 2022","Unit 3: Macroeconomics","3.3 Macroeconomic objectives","3.3.5 Sustainable level of government (national) debt","First exams 2022","Unit 3: Macroeconomics","3.3 Macroeconomic objectives","First exams 2022","Unit 3: Macroeconomics"],"memberSectionIds":[],"sectionOrders":{}}}