{"questionId":"9972","questionHtml":"<p>Explain <strong>two</strong> reasons why Chinese companies may have been attracted into Peru (paragraph <strong>[4]</strong>).</p>","markschemeHtml":"<p><img src=\"__IMG__/4484f5f13cc4fcd45dd7994d573aebb5a195a7b6.png\"></p>","meta":{"questionId":"9972","referenceCode":"19M.2.SL.TZ0.4b","subjectId":"48-dp-economics","title":"Explain two reasons why Chinese companies may have been attracted into Peru (paragraph [4]).","paper":"2","level":"SL","questionNumber":"b","marksAvailable":"[Maximum mark: 4]","breadcrumbLabels":["First exams 2022","Last exams 2021","Last exams 2021","Section 4: Development economics","First exams 2022","Unit 4: The global economy","4.10 Economic growth and/or economic development strategies","4.10.1 Strategies to promote economic growth and/or economic development","First exams 2022","Unit 4: The global economy","4.10 Economic growth and/or economic development strategies","First exams 2022","Unit 4: The global economy","Last exams 2021","Section 4: Development economics","4.5 The role of foreign direct investment (FDI)","Foreign direct investment and multinational corporations (MNCs)","The meaning of FDI and MNCs","Last exams 2021","Section 4: Development economics","4.5 The role of foreign direct investment (FDI)","Foreign direct investment and multinational corporations (MNCs)","Last exams 2021","Section 4: Development economics","4.5 The role of foreign direct investment (FDI)"],"memberSectionIds":[],"sectionOrders":{}}}