{"questionId":"13987","questionHtml":"<div class=\"qb-parent-stem\"><p>Let&nbsp;<span class=\"mjpage\"><math xmlns=\"http://www.w3.org/1998/Math/MathML\" alttext=\"f\\left( x \\right) = \\frac{{16}}{x}\">\n  <mi>f</mi>\n  <mrow>\n    <mo>(</mo>\n    <mi>x</mi>\n    <mo>)</mo>\n  </mrow>\n  <mo>=</mo>\n  <mfrac>\n    <mrow>\n      <mn>16</mn>\n    </mrow>\n    <mi>x</mi>\n  </mfrac>\n</math></span>. The line <span class=\"mjpage\"><math xmlns=\"http://www.w3.org/1998/Math/MathML\" alttext=\"L\">\n  <mi>L</mi>\n</math></span>&nbsp;is tangent to the graph of&nbsp;<span class=\"mjpage\"><math xmlns=\"http://www.w3.org/1998/Math/MathML\" alttext=\"f\">\n  <mi>f</mi>\n</math></span> at&nbsp;<span class=\"mjpage\"><math xmlns=\"http://www.w3.org/1998/Math/MathML\" alttext=\"x = 8\">\n  <mi>x</mi>\n  <mo>=</mo>\n  <mn>8</mn>\n</math></span>.</p></div>\n<div class=\"qb-parent-stem\"><p><span class=\"mjpage\"><math xmlns=\"http://www.w3.org/1998/Math/MathML\" alttext=\"L\">\n  <mi>L</mi>\n</math></span> can be expressed in the form <em><strong>r</strong></em>&nbsp;<span class=\"mjpage\"><math xmlns=\"http://www.w3.org/1998/Math/MathML\" alttext=\" = \\left( {\\begin{array}{*{20}{c}}  8 \\\\   2  \\end{array}} \\right) + t\">\n  <mo>=</mo>\n  <mrow>\n    <mo>(</mo>\n    <mrow>\n      <mtable rowspacing=\"4pt\" columnspacing=\"1em\">\n        <mtr>\n          <mtd>\n            <mn>8</mn>\n          </mtd>\n        </mtr>\n        <mtr>\n          <mtd>\n            <mn>2</mn>\n          </mtd>\n        </mtr>\n      </mtable>\n    </mrow>\n    <mo>)</mo>\n  </mrow>\n  <mo>+</mo>\n  <mi>t</mi>\n</math></span><em><strong>u</strong></em>.</p></div>\n<div class=\"qb-parent-stem\"><p>The direction vector of <span class=\"mjpage\"><math xmlns=\"http://www.w3.org/1998/Math/MathML\" alttext=\"y = x\">\n  <mi>y</mi>\n  <mo>=</mo>\n  <mi>x</mi>\n</math></span> is&nbsp;<span class=\"mjpage\"><math xmlns=\"http://www.w3.org/1998/Math/MathML\" alttext=\"\\left( {\\begin{array}{*{20}{c}}  1 \\\\   1  \\end{array}} \\right)\">\n  <mrow>\n    <mo>(</mo>\n    <mrow>\n      <mtable rowspacing=\"4pt\" columnspacing=\"1em\">\n        <mtr>\n          <mtd>\n            <mn>1</mn>\n          </mtd>\n        </mtr>\n        <mtr>\n          <mtd>\n            <mn>1</mn>\n          </mtd>\n        </mtr>\n      </mtable>\n    </mrow>\n    <mo>)</mo>\n  </mrow>\n</math></span>.</p></div>\n<div class=\"qb-leaf-prompt\"><p>Find&nbsp;<span class=\"mjpage\"><math xmlns=\"http://www.w3.org/1998/Math/MathML\" alttext=\"\\left( {f \\circ f} \\right)\\left( x \\right)\"> <mrow> <mo>(</mo> <mrow> <mi>f</mi> <mo>∘</mo> <mi>f</mi> </mrow> <mo>)</mo> </mrow> <mrow> <mo>(</mo> <mi>x</mi> <mo>)</mo> </mrow> </math></span>.</p></div>","markschemeHtml":"<p><span style=\"font-size:10.5pt;font-family:'Verdana' , sans-serif;color:black;\">attempt to form composite&nbsp;<span class=\"mjpage\"><math xmlns=\"http://www.w3.org/1998/Math/MathML\" alttext=\"\\left( {f \\circ f} \\right)\\left( x \\right)\"> <mrow> <mo>(</mo> <mrow> <mi>f</mi> <mo>∘</mo> <mi>f</mi> </mrow> <mo>)</mo> </mrow> <mrow> <mo>(</mo> <mi>x</mi> <mo>)</mo> </mrow> </math></span>&nbsp; &nbsp; &nbsp;<strong><em><span style=\"font-family:'Verdana' , sans-serif;\">(M1)</span></em></strong></span></p>\n<p><em><span style=\"font-size:10.5pt;font-family:'Verdana' , sans-serif;color:black;\">eg&nbsp;</span></em><span style=\"font-size:10.5pt;font-family:'Verdana' , sans-serif;color:black;\">&nbsp;&nbsp;<span class=\"mjpage\"><math xmlns=\"http://www.w3.org/1998/Math/MathML\" alttext=\"f\\left( {f\\left( x \\right)} \\right)\"> <mi>f</mi> <mrow> <mo>(</mo> <mrow> <mi>f</mi> <mrow> <mo>(</mo> <mi>x</mi> <mo>)</mo> </mrow> </mrow> <mo>)</mo> </mrow> </math></span> ,&nbsp;&nbsp;<span class=\"mjpage\"><math xmlns=\"http://www.w3.org/1998/Math/MathML\" alttext=\"f\\left( {\\frac{{16}}{x}} \\right)\"> <mi>f</mi> <mrow> <mo>(</mo> <mrow> <mfrac> <mrow> <mn>16</mn> </mrow> <mi>x</mi> </mfrac> </mrow> <mo>)</mo> </mrow> </math></span> ,&nbsp;&nbsp;<span class=\"mjpage\"><math xmlns=\"http://www.w3.org/1998/Math/MathML\" alttext=\"\\frac{{16}}{{f\\left( x \\right)}}\"> <mfrac> <mrow> <mn>16</mn> </mrow> <mrow> <mi>f</mi> <mrow> <mo>(</mo> <mi>x</mi> <mo>)</mo> </mrow> </mrow> </mfrac> </math></span></span></p>\n<p><span style=\"font-size:10.5pt;font-family:'Verdana' , sans-serif;color:black;\">correct working&nbsp; &nbsp; &nbsp;<strong><em><span style=\"font-family:'Verdana' , sans-serif;\">(A1)</span></em></strong></span></p>\n<p><span style=\"font-size:10.5pt;font-family:'Verdana' , sans-serif;color:black;\"><em>eg</em>&nbsp; <span class=\"mjpage\"><math xmlns=\"http://www.w3.org/1998/Math/MathML\" alttext=\"\\frac{{16}}{{\\frac{{16}}{x}}}\"> <mfrac> <mrow> <mn>16</mn> </mrow> <mrow> <mfrac> <mrow> <mn>16</mn> </mrow> <mi>x</mi> </mfrac> </mrow> </mfrac> </math></span>&nbsp;,&nbsp;&nbsp;<span class=\"mjpage\"><math xmlns=\"http://www.w3.org/1998/Math/MathML\" alttext=\"16 \\times \\frac{x}{{16}}\"> <mn>16</mn> <mo>×</mo> <mfrac> <mi>x</mi> <mrow> <mn>16</mn> </mrow> </mfrac> </math></span></span></p>\n<p><span style=\"font-size:10.5pt;font-family:'Verdana' , sans-serif;color:black;\"><span class=\"mjpage\"><math xmlns=\"http://www.w3.org/1998/Math/MathML\" alttext=\"\\left( {f \\circ f} \\right)\\left( x \\right) = x\"> <mrow> <mo>(</mo> <mrow> <mi>f</mi> <mo>∘</mo> <mi>f</mi> </mrow> <mo>)</mo> </mrow> <mrow> <mo>(</mo> <mi>x</mi> <mo>)</mo> </mrow> <mo>=</mo> <mi>x</mi> </math></span>&nbsp; &nbsp; &nbsp;<strong><em><span style=\"font-family:'Verdana' , sans-serif;\">A1 N2</span></em></strong></span></p>\n<p><strong><em><span style=\"font-size:10.5pt;font-family:'Verdana' , sans-serif;color:black;\">[3 marks]</span></em></strong></p>","meta":{"questionId":"13987","referenceCode":"19M.2.SL.TZ1.S_9d.i","subjectId":"50-dp-mathematics-analysis-and-approaches","title":"Find ( f ∘ f ) ( x ) .","paper":"2","level":"SL","questionNumber":"d.i","marksAvailable":"[Maximum mark: 3]","breadcrumbLabels":["Topic 5 —Calculus","Topic 5 —Calculus","SL 5.4—Tangents and normal"],"memberSectionIds":[],"sectionOrders":{}},"schemaVersion":2}