{"questionId":"17530","questionHtml":"<div class=\"qb-parent-stem\"><p>SpeedWay airline flies from city <span class=\"mjpage\"><math xmlns=\"http://www.w3.org/1998/Math/MathML\" alttext=\"{\\text{A}}\">\n  <mrow>\n    <mtext>A</mtext>\n  </mrow>\n</math></span> to city <span class=\"mjpage\"><math xmlns=\"http://www.w3.org/1998/Math/MathML\" alttext=\"{\\text{B}}\">\n  <mrow>\n    <mtext>B</mtext>\n  </mrow>\n</math></span>. The flight time is normally distributed with a mean of <span class=\"mjpage\"><math xmlns=\"http://www.w3.org/1998/Math/MathML\" alttext=\"260\">\n  <mn>260</mn>\n</math></span> minutes and a standard deviation of <span class=\"mjpage\"><math xmlns=\"http://www.w3.org/1998/Math/MathML\" alttext=\"15\">\n  <mn>15</mn>\n</math></span> minutes.</p>\n<p>A flight is considered late if it takes longer than <span class=\"mjpage\"><math xmlns=\"http://www.w3.org/1998/Math/MathML\" alttext=\"275\">\n  <mn>275</mn>\n</math></span> minutes.</p></div>\n<div class=\"qb-parent-stem\"><p>The flight is considered to be <strong>on time</strong> if it takes between <span class=\"mjpage\"><math xmlns=\"http://www.w3.org/1998/Math/MathML\" alttext=\"m\">\n  <mi>m</mi>\n</math></span> and <span class=\"mjpage\"><math xmlns=\"http://www.w3.org/1998/Math/MathML\" alttext=\"275\">\n  <mn>275</mn>\n</math></span> minutes. The probability that a flight is on time is <span class=\"mjpage\"><math xmlns=\"http://www.w3.org/1998/Math/MathML\" alttext=\"0.830\">\n  <mn>0.830</mn>\n</math></span>.</p></div>\n<div class=\"qb-leaf-prompt\"><p>Find the value of <span class=\"mjpage\"><math xmlns=\"http://www.w3.org/1998/Math/MathML\" alttext=\"m\"> <mi>m</mi> </math></span>.</p></div>","markschemeHtml":"<p>valid approach &nbsp; &nbsp; &nbsp;&nbsp;<em><strong>(M1)</strong></em></p>\n<p><em>eg</em>&nbsp; &nbsp; &nbsp; <span class=\"mjpage\"><math xmlns=\"http://www.w3.org/1998/Math/MathML\" alttext=\"{\\text{P}}\\left( {X < 275} \\right) - {\\text{P}}\\left( {X < m} \\right) = 0.830\"> <mrow> <mtext>P</mtext> </mrow> <mrow> <mo>(</mo> <mrow> <mi>X</mi> <mo>&lt;</mo> <mn>275</mn> </mrow> <mo>)</mo> </mrow> <mo>−</mo> <mrow> <mtext>P</mtext> </mrow> <mrow> <mo>(</mo> <mrow> <mi>X</mi> <mo>&lt;</mo> <mi>m</mi> </mrow> <mo>)</mo> </mrow> <mo>=</mo> <mn>0.830</mn> </math></span></p>\n<p>correct working&nbsp;&nbsp; &nbsp; &nbsp;&nbsp;<em><strong>(A1)</strong></em></p>\n<p><em>eg</em>&nbsp; &nbsp; &nbsp;&nbsp;<span class=\"mjpage\"><math xmlns=\"http://www.w3.org/1998/Math/MathML\" alttext=\"{\\text{P}}\\left( {X < m} \\right) = 0.0113447\"> <mrow> <mtext>P</mtext> </mrow> <mrow> <mo>(</mo> <mrow> <mi>X</mi> <mo>&lt;</mo> <mi>m</mi> </mrow> <mo>)</mo> </mrow> <mo>=</mo> <mn>0.0113447</mn> </math></span></p>\n<p><span class=\"mjpage\"><math xmlns=\"http://www.w3.org/1998/Math/MathML\" alttext=\"225.820\"> <mn>225.820</mn> </math></span></p>\n<p><span class=\"mjpage\"><math xmlns=\"http://www.w3.org/1998/Math/MathML\" alttext=\"226\"> <mn>226</mn> </math></span> (minutes)&nbsp; &nbsp; &nbsp;&nbsp;<em><strong>A1&nbsp; &nbsp;N3</strong></em></p>\n<p><em><strong>[3 marks]</strong></em></p>","meta":{"questionId":"17530","referenceCode":"19N.2.SL.TZ0.S_9b","subjectId":"50-dp-mathematics-analysis-and-approaches","title":"Find the value of m .","paper":"2","level":"SL","questionNumber":"b","marksAvailable":"[Maximum mark: 3]","breadcrumbLabels":["Topic 2—Functions","Topic 4—Statistics and probability","Topic 4—Statistics and probability","SL 4.6—Combined, mutually exclusive, conditional, independence, prob diagrams","Topic 4—Statistics and probability","SL 4.8—Binomial distribution","Topic 4—Statistics and probability","SL 4.9—Normal distribution and calculations","Topic 2—Functions","SL 2.10—Solving equations graphically and analytically"],"memberSectionIds":[],"sectionOrders":{}},"schemaVersion":2}