{"questionId":"25688","questionHtml":"<p>Find <math xmlns=\"http://www.w3.org/1998/Math/MathML\"><mtext>P</mtext><mo>(</mo><mi>X</mi><mo>&gt;</mo><mn>2</mn><mo>)</mo></math>.</p>","markschemeHtml":"<p>valid approach &nbsp; &nbsp; &nbsp; &nbsp;<strong><em>(M1)</em></strong></p>\n<p><math xmlns=\"http://www.w3.org/1998/Math/MathML\"><mtext>P</mtext><mo>(</mo><mi>X</mi><mo>&gt;</mo><mn>2</mn><mo>)</mo><mo>=</mo><mtext>P</mtext><mo>(</mo><mi>X</mi><mo>=</mo><mn>3</mn><mo>)</mo><mo>+</mo><mtext>P</mtext><mo>(</mo><mi>X</mi><mo>=</mo><mn>4</mn><mo>)</mo></math>&nbsp; OR&nbsp;&nbsp;<math xmlns=\"http://www.w3.org/1998/Math/MathML\"><mtext>P</mtext><mo>(</mo><mi>X</mi><mo>&gt;</mo><mn>2</mn><mo>)</mo><mo>=</mo><mn>1</mn><mo>-</mo><mtext>P</mtext><mo>(</mo><mi>X</mi><mo>=</mo><mn>1</mn><mo>)</mo><mo>-</mo><mtext>P</mtext><mo>(</mo><mi>X</mi><mo>=</mo><mn>2</mn><mo>)</mo></math></p>\n<p><math xmlns=\"http://www.w3.org/1998/Math/MathML\"><mo>=</mo><mn>0</mn><mo>.</mo><mn>3</mn></math>&nbsp; &nbsp; &nbsp; &nbsp; &nbsp;&nbsp;<em><strong>A1</strong></em></p>\n<p>&nbsp;</p>\n<p><em><strong>[2 marks]</strong></em></p>","meta":{"questionId":"25688","referenceCode":"22M.1.SL.TZ2.9b","subjectId":"50-dp-mathematics-analysis-and-approaches","title":"Find P(X>2).","paper":"1","level":"SL","questionNumber":"b","marksAvailable":"[Maximum mark: 2]","breadcrumbLabels":["Topic 4—Statistics and probability","Topic 4—Statistics and probability","SL 4.7—Discrete random variables"],"memberSectionIds":[],"sectionOrders":{}}}