{"questionId":"25921","questionHtml":"<p>State why it appears that the mean reaction time is greater than the median reaction time.</p>","markschemeHtml":"<p><strong>EITHER</strong></p>\n<p>the median is closer to the lower quartile (positively skewed)&nbsp;&nbsp; &nbsp; &nbsp; &nbsp;<em><strong>R1</strong></em></p>\n<p><br><strong>OR</strong></p>\n<p>The distribution is positively skewed&nbsp;&nbsp; &nbsp; &nbsp; &nbsp;<em><strong>R1</strong></em></p>\n<p><br><strong>OR</strong></p>\n<p>the range of reaction times below the median is smaller than the range of reaction&nbsp;times above the median &nbsp; &nbsp; &nbsp; &nbsp;<em><strong>R1</strong></em></p>\n<p>&nbsp;</p>\n<p><strong>Note:</strong> These are sample answers from a range of acceptable correct answers. Award <em><strong>R1</strong></em> for any correct statement that explains this.<br>Do not award <em><strong>R1</strong></em> if there is also an incorrect statement, even if another&nbsp;statement in the answer is correct. Accept a correctly and clearly labelled&nbsp;diagram.</p>\n<p>&nbsp;</p>\n<p><em><strong>[1 mark]</strong></em></p>","meta":{"questionId":"25921","referenceCode":"22M.2.SL.TZ2.5c","subjectId":"50-dp-mathematics-analysis-and-approaches","title":"State why it appears that the mean reaction time is greater than the median reaction time.","paper":"2","level":"SL","questionNumber":"c","marksAvailable":"[Maximum mark: 1]","breadcrumbLabels":["Topic 4—Statistics and probability","Topic 4—Statistics and probability","SL 4.2—Histograms, CF graphs, box plots"],"memberSectionIds":[],"sectionOrders":{}}}