{"questionId":"25998","questionHtml":"<p>After <math xmlns=\"http://www.w3.org/1998/Math/MathML\"><mn>10</mn></math> years, the population of marsupials is <math xmlns=\"http://www.w3.org/1998/Math/MathML\"><mn>3</mn><msub><mi>P</mi><mn>0</mn></msub></math>. It is known that <math xmlns=\"http://www.w3.org/1998/Math/MathML\"><mi>N</mi><mo>=</mo><mn>4</mn><msub><mi>P</mi><mn>0</mn></msub></math>.</p>\n<p>Find the value of <math xmlns=\"http://www.w3.org/1998/Math/MathML\"><mi>k</mi></math> for this population model.</p>","markschemeHtml":"<p>substitutes&nbsp;<math xmlns=\"http://www.w3.org/1998/Math/MathML\"><mi>t</mi><mo>=</mo><mn>10</mn><mo>,</mo><mo>&nbsp;</mo><mi>P</mi><mo>=</mo><mn>3</mn><msub><mi>P</mi><mn>0</mn></msub></math>&nbsp;and&nbsp;<math xmlns=\"http://www.w3.org/1998/Math/MathML\"><mi>N</mi><mo>=</mo><mn>4</mn><msub><mi>P</mi><mn>0</mn></msub></math>&nbsp;into&nbsp;<math xmlns=\"http://www.w3.org/1998/Math/MathML\"><mi>k</mi><mi>t</mi><mo>=</mo><mi>ln</mi><mfrac><mi>P</mi><msub><mi>P</mi><mn>0</mn></msub></mfrac><mfenced><mfrac><mrow><mi>N</mi><mo>-</mo><msub><mi>P</mi><mn>0</mn></msub></mrow><mrow><mi>N</mi><mo>-</mo><mi>P</mi></mrow></mfrac></mfenced></math>&nbsp; &nbsp; &nbsp; &nbsp; &nbsp;&nbsp;<em><strong>M1</strong></em></p>\n<p><math xmlns=\"http://www.w3.org/1998/Math/MathML\"><mn>10</mn><mi>k</mi><mo>=</mo><mi>ln</mi><mo> </mo><mn>3</mn><mfenced><mfrac><mrow><mn>4</mn><msub><mi>P</mi><mn>0</mn></msub><mo>-</mo><msub><mi>P</mi><mn>0</mn></msub></mrow><mrow><mn>4</mn><msub><mi>P</mi><mn>0</mn></msub><mo>-</mo><mn>3</mn><msub><mi>P</mi><mn>0</mn></msub></mrow></mfrac></mfenced><mo>&nbsp;</mo><mo>&nbsp;</mo><mfenced><mrow><mo>=</mo><mi>ln</mi><mo> </mo><mn>9</mn></mrow></mfenced></math></p>\n<p><math xmlns=\"http://www.w3.org/1998/Math/MathML\"><mi>k</mi><mo>=</mo><mn>0</mn><mo>.</mo><mn>220</mn><mo>&nbsp;</mo><mo>&nbsp;</mo><mfenced><mrow><mo>=</mo><mfrac><mn>1</mn><mn>10</mn></mfrac><mi>ln</mi><mo> </mo><mn>9</mn><mo>,</mo><mo>=</mo><mfrac><mn>1</mn><mn>5</mn></mfrac><mi>ln</mi><mo> </mo><mn>3</mn></mrow></mfenced></math>&nbsp;&nbsp; &nbsp; &nbsp; &nbsp;&nbsp;<em><strong>A1</strong></em></p>\n<p>&nbsp;</p>\n<p><em><strong>[2 marks]</strong></em></p>","meta":{"questionId":"25998","referenceCode":"22M.2.AHL.TZ2.12f","subjectId":"50-dp-mathematics-analysis-and-approaches","title":"After 10 years, the population of marsupials is 3P0. It is known that N=4P0. Find the value of k for this population model.","paper":"2","level":"AHL","questionNumber":"f","marksAvailable":"[Maximum mark: 2]","breadcrumbLabels":["Topic 2—Functions","Topic 2—Functions","SL 2.10—Solving equations graphically and analytically"],"memberSectionIds":[],"sectionOrders":{}}}