{"questionId":"33605279","questionHtml":"<p>Write down the amplitude of the graph of <math xmlns=\"http://www.w3.org/1998/Math/MathML\"><mi>f</mi></math>.</p>","markschemeHtml":"<p>6<em><strong>&nbsp;&nbsp;&nbsp;&nbsp;&nbsp;&nbsp;&nbsp;&nbsp;&nbsp; </strong><strong>A1</strong></em></p>\n<p style=\"text-align:right;\"><em><strong>[1 mark]</strong></em></p>","meta":{"questionId":"33605279","referenceCode":"24N.2.SL.TZ2.9ai","subjectId":"50-dp-mathematics-analysis-and-approaches","title":"Write down the amplitude of the graph of f.","paper":"2","level":"SL","questionNumber":"i","marksAvailable":"[Maximum mark: 1]","breadcrumbLabels":["Topic 3— Geometry and trigonometry","Topic 3— Geometry and trigonometry","SL 3.7—Circular functions: graphs, composites, transformations"],"memberSectionIds":[],"sectionOrders":{}},"schemaVersion":2}