{"questionId":"9378","questionHtml":"<p>Find E(<em>Y</em>).</p>","markschemeHtml":"<p>recognizing binomial probability&nbsp; &nbsp; &nbsp; <em><strong>(M1)</strong></em></p>\n<p>E(<em>Y</em>) = 10 × 0.10621&nbsp; &nbsp; &nbsp; &nbsp;<em><strong>(A1)</strong></em></p>\n<p>=&nbsp;1.06&nbsp; &nbsp; &nbsp; &nbsp; &nbsp;<em><strong>A1 &nbsp;</strong></em></p>\n<p><em><strong>[3 marks]</strong></em></p>","meta":{"questionId":"9378","referenceCode":"SPM.2.SL.TZ0.8c","subjectId":"50-dp-mathematics-analysis-and-approaches","title":"Find E(Y).","paper":"2","level":"SL","questionNumber":"c","marksAvailable":"[Maximum mark: 3]","breadcrumbLabels":["Topic 4—Statistics and probability","Topic 4—Statistics and probability","SL 4.6—Combined, mutually exclusive, conditional, independence, prob diagrams","Topic 4—Statistics and probability","SL 4.8—Binomial distribution","Topic 4—Statistics and probability","SL 4.9—Normal distribution and calculations"],"memberSectionIds":[],"sectionOrders":{}}}