{"questionId":"4248","questionHtml":"<p>Which of these structures is not homologous?</p>\n<p>&nbsp;</p>\n<p><img src=\"__IMG__/bcf39602627a1a6cc7ddef289002cccdb2fcff1f.png\" width=\"494\" height=\"278\"></p>\n<p>[Source: https://en.wikipedia.org/wiki/Comparative_anatomy#/media/File:Homology_vertebrates-en.svg and<br><a href=\"https://commons.wikimedia.org/wiki/File:Insect_leg_scheme.svg%5D\">https://commons.wikimedia.org/wiki/File:Insect_leg_scheme.svg]</a></p>\n<p>&nbsp;</p>","markschemeHtml":"<p>C</p>","meta":{"questionId":"4248","referenceCode":"17N.1.SL.TZ0.20","subjectId":"43-dp-biology-last-assessment-2024","title":"Which of these structures is not homologous? [Source: https://en.wikipedia.org/wiki/Comparative_anatomy#/media/File:Homology_vertebrates-en.svg andhttps://commons.wikimedia.org/wik","paper":"1","level":"SL","questionNumber":"20","marksAvailable":"[Maximum mark: 1]","breadcrumbLabels":["Core","Core","Topic 5: Evolution and biodiversity","5.1 Evidence for evolution","Core","Topic 5: Evolution and biodiversity"],"memberSectionIds":[],"sectionOrders":{}}}