{"questionId":"5004414","questionHtml":"<p>The diagram shows the carbon cycle.</p>\n<p><img style=\"display:block;margin-left:auto;margin-right:auto;\" src=\"__IMG__/21debc330a7c1f39571176d7cbf8634ff6033b55.png\"></p>\n<p>&nbsp;</p>\n<p>Which letters represent respiration?</p>\n<p><br>A.&nbsp; R and T</p>\n<p>B.&nbsp; P and V</p>\n<p>C.&nbsp; Q and R</p>\n<p>D.&nbsp; R and V</p>","markschemeHtml":"<p>D</p>","meta":{"questionId":"5004414","referenceCode":"23M.1.SL.TZ2.20","subjectId":"43-dp-biology-last-assessment-2024","title":"The diagram shows the carbon cycle. Which letters represent respiration? A. R and T B. P and V C. Q and R D. R and V","paper":"1","level":"SL","questionNumber":"20","marksAvailable":"[Maximum mark: 1]","breadcrumbLabels":["Core","Core","Topic 4: Ecology","4.2 Energy flow","Core","Topic 4: Ecology"],"memberSectionIds":[],"sectionOrders":{}}}