{"questionId":"6590","questionHtml":"<div class=\"qb-parent-stem\"><p>The graph shows the relationship between the maximum heart rate during exercise and a person’s age.</p>\n<p style=\"text-align:center;\"><img src=\"__IMG__/ed3d91676f52a4067e8b46ef62a384f86f0a42bf.png\"></p></div>\n<div class=\"qb-leaf-prompt\"><p>Suggest reasons for the change in maximum heart rate with increasing age.</p></div>","markschemeHtml":"<p>a. muscles become less elastic<br><em><strong>OR</strong></em><br>less muscle tone&nbsp;</p>\n<p>b. cells/mitochondria less efficient&nbsp;&nbsp;</p>\n<p>c. more fat deposits<br><em><strong>OR</strong></em><br>blood/oxygen supply to heart tissue reduced</p>\n<p><em>Accept other valid documented answers</em>.&nbsp;</p>","meta":{"questionId":"6590","referenceCode":"18M.3.HL.TZ2.22b","subjectId":"43-dp-biology-last-assessment-2024","title":"Suggest reasons for the change in maximum heart rate with increasing age.","paper":"3","level":"HL","questionNumber":"b","marksAvailable":"[Maximum mark: 2]","breadcrumbLabels":["Option D: Human physiology","Option D: Human physiology","Option D: Human physiology (Core topics)","D.4 The heart","Option D: Human physiology","Option D: Human physiology (Core topics)"],"memberSectionIds":[],"sectionOrders":{}},"schemaVersion":2}