{"questionId":"7142","questionHtml":"<div class=\"qb-parent-stem\"><p>The food conversion ratio (FCR) is the ratio between the mass of food given to a farmed animal and its corresponding increase in mass. The first bar chart shows the FCR for four farmed animals. The second bar chart shows the percentage yield of edible meat provided by each whole animal.</p>\n<p style=\"text-align:center;\"><img src=\"__IMG__/c0089cfcc67e0a9a6d9449006cf9de3ec9e9fc72.png\"></p></div>\n<div class=\"qb-leaf-prompt\"><p style=\"text-align:left;\">Calculate how much food would be required to produce 20 kg of boar meat.</p>\n<p style=\"text-align:left;\"><img src=\"__IMG__/305f56f8a969ec65a6c3f6066f95c3017658ca3d.png\"></p></div>","markschemeHtml":"<p style=\"text-align:left;\">120 kg&nbsp;✔</p>\n<p style=\"text-align:left;\"><em>Working not required</em></p>","meta":{"questionId":"7142","referenceCode":"18N.3.SL.TZ0.12b","subjectId":"43-dp-biology-last-assessment-2024","title":"Calculate how much food would be required to produce 20 kg of boar meat.","paper":"3","level":"SL","questionNumber":"b","marksAvailable":"[Maximum mark: 1]","breadcrumbLabels":["Option C: Ecology and conservation","Option C: Ecology and conservation","Option C: Ecology and conservation (Core topics)","C.2 Communities and ecosystems","Option C: Ecology and conservation","Option C: Ecology and conservation (Core topics)"],"memberSectionIds":[],"sectionOrders":{}},"schemaVersion":2}