{"questionId":"9078439","questionHtml":"<p>A respirometer is used to measure the oxygen consumption of germinating seeds. The distance that the oil drop moves is measured at 15-minute intervals.</p>\n<p style=\"text-align:center;\"><img src=\"__IMG__/4adc5920872e9680c26c9bd61ba3cf5ea760de90.png\"></p>\n<p style=\"text-align:center;\">[Source: © The Royal Society of Biology.]</p>\n<p style=\"text-align:left;\">&nbsp;</p>\n<p style=\"text-align:left;\">What is the function of chemical X?</p>\n<p style=\"text-align:left;\">A. Absorbs carbon dioxide so the oxygen released by the seeds can be measured</p>\n<p style=\"text-align:left;\">B. Absorbs carbon dioxide so the oxygen absorbed by the seeds can be measured</p>\n<p style=\"text-align:left;\">C. Absorbs oxygen so the carbon dioxide released by the seeds can be measured</p>\n<p style=\"text-align:left;\">D. Absorbs oxygen so the carbon dioxide absorbed by the seeds can be measured</p>","markschemeHtml":"<p>B</p>","meta":{"questionId":"9078439","referenceCode":"21N.1.SL.TZ0.12","subjectId":"43-dp-biology-last-assessment-2024","title":"A respirometer is used to measure the oxygen consumption of germinating seeds. The distance that the oil drop moves is measured at 15-minute intervals. [Source: © The Royal Society","paper":"1","level":"SL","questionNumber":"12","marksAvailable":"[Maximum mark: 1]","breadcrumbLabels":["Core","Core","Topic 2: Molecular biology","2.8 Cell respiration","Core","Topic 2: Molecular biology"],"memberSectionIds":[],"sectionOrders":{}},"schemaVersion":2}