{"questionId":"9078800","questionHtml":"<p>The graph shows the effect of increasing substrate concentration on the rate of an enzyme-catalysed reaction.</p>\n<p style=\"text-align:center;\"><img src=\"__IMG__/352959d8be45d89071a816ccba137c1989dc1c2e.png\"></p>\n<p style=\"text-align:left;\">&nbsp;</p>\n<p style=\"text-align:left;\">Which type of inhibition corresponds to the labelled curves?</p>\n<p style=\"text-align:center;\"><img style=\"float:left;\" src=\"__IMG__/5fb735890fcec401fba0337cbbe252fa51f95ccc.png\"></p>\n<p style=\"text-align:center;\">&nbsp;</p>","markschemeHtml":"<p>B</p>","meta":{"questionId":"9078800","referenceCode":"22M.1.HL.TZ1.29","subjectId":"43-dp-biology-last-assessment-2024","title":"The graph shows the effect of increasing substrate concentration on the rate of an enzyme-catalysed reaction. Which type of inhibition corresponds to the labelled curves?","paper":"1","level":"HL","questionNumber":"29","marksAvailable":"[Maximum mark: 1]","breadcrumbLabels":["Additional higher level","Additional higher level","Topic 8: Metabolism, cell respiration and photosynthesis","8.1 Metabolism","Additional higher level","Topic 8: Metabolism, cell respiration and photosynthesis"],"memberSectionIds":[],"sectionOrders":{}}}