{"questionId":"9079264","questionHtml":"<p>State <strong>one</strong> possible use of hybridoma cells.</p>","markschemeHtml":"<p>produce monoclonal antibodies<br><em><strong>OR</strong></em><br>diagnosis of diseases/malaria/cancer/HIV<br><em><strong>OR</strong></em><br>treatment of rabies<br><em><strong>OR</strong></em><br>blood and tissue typing<br><em><strong>OR</strong></em><br>pregnancy testing<br><em><strong>OR</strong></em><br>targeting of cancer cells «with a chemotherapy drug»<br><em><strong>OR</strong></em><br>treatment of infection if too late for vaccination/successful immune response</p>\n<p><em>Only accept the first use of hybridoma cells given in the answer</em></p>\n<p><em>Not treatment of malaria</em></p>\n<p>&nbsp;</p>","meta":{"questionId":"9079264","referenceCode":"17N.2.HL.TZ0.d.ii","subjectId":"43-dp-biology-last-assessment-2024","title":"State one possible use of hybridoma cells.","paper":"2","level":"HL","questionNumber":"d.ii","marksAvailable":"[Maximum mark: 1]","breadcrumbLabels":["Additional higher level","Additional higher level","Topic 11: Animal physiology"],"memberSectionIds":[],"sectionOrders":{}},"schemaVersion":2}