{"questionId":"9080706","questionHtml":"<p>Explain biogeographic factors that increase the effectiveness of nature reserves.</p>","markschemeHtml":"<p>a. large area can support greater range of habitats / longer food chains / higher population numbers&nbsp;</p>\n<p>b. low edge effect with circular reserves</p>\n<p><em><strong>OR</strong></em></p>\n<p>reduced edge effect minimises area that is disturbed/competition&nbsp;</p>\n<p>c. intact / unbroken areas represent less disturbance on habitats&nbsp;</p>\n<p>d. fragmented areas linked by corridors&nbsp;</p>\n<p>e. (proximity of fragmented areas) allows for animal movement / genetic exchange</p>","meta":{"questionId":"9080706","referenceCode":"18M.3.HL.TZ1.b","subjectId":"43-dp-biology-last-assessment-2024","title":"Explain biogeographic factors that increase the effectiveness of nature reserves.","paper":"3","level":"HL","questionNumber":"b","marksAvailable":"[Maximum mark: 3]","breadcrumbLabels":["Option C: Ecology and conservation","Option C: Ecology and conservation","Option C: Ecology and conservation (Core topics)","C.4 Conservation of biodiversity","Option C: Ecology and conservation","Option C: Ecology and conservation (Core topics)"],"memberSectionIds":[],"sectionOrders":{}}}