{"questionId":"9080504","questionHtml":"<div class=\"qb-parent-stem\"><p>All living organisms depend on a continuous supply of energy.</p></div>\n<div class=\"qb-leaf-prompt\"><p>Describe the reasons for the shape of a pyramid of energy.</p></div>","markschemeHtml":"<p>a. pyramid of energy has stepped shape with largest bottom step being producers, then first consumer, second consumer, <em>etc</em>&nbsp;<br><br>b. light energy «from sun» converted to chemical energy in carbon compounds by photosynthesis&nbsp;</p>\n<p>c. energy released by respiration is used in living organisms <em><strong>AND</strong></em> converted to heat&nbsp;</p>\n<p>d. heat «energy» is lost from ecosystems&nbsp;</p>\n<p>e. approximately 10 % of energy in trophic level converted into new material for next level&nbsp;</p>\n<p>f. energy also lost as undigested material/uneaten material/feces/excretion&nbsp;</p>","meta":{"questionId":"9080504","referenceCode":"18M.2.HL.TZ2.c","subjectId":"43-dp-biology-last-assessment-2024","title":"Describe the reasons for the shape of a pyramid of energy.","paper":"2","level":"HL","questionNumber":"c","marksAvailable":"[Maximum mark: 3]","breadcrumbLabels":["Core","Core","Topic 4: Ecology","4.2 Energy flow","Core","Topic 4: Ecology"],"memberSectionIds":[],"sectionOrders":{}},"schemaVersion":2}