{"questionId":"9081173","questionHtml":"<p style=\"text-align:left;\">Explain the changes in ventilation after 35 seconds.</p>","markschemeHtml":"<p>a. the volume of air per breath increases<br><em><strong>OR</strong></em><br>the volume of each breath reaches a maximum/levels off<br><em><strong>OR</strong></em><br>frequency of ventilation/breaths per minute increases&nbsp;✔</p>\n<p>b. exercise increases «rate of cellular» respiration/energy use/blood CO<sub>2</sub>/acidity&nbsp;✔</p>\n<p>c. exercise causes increased demand for oxygen/removal of carbon dioxide&nbsp;✔</p>\n<p>d. maximum rate/depth of ventilation is determined by the capacity of the student&nbsp;✔</p>","meta":{"questionId":"9081173","referenceCode":"18N.3.SL.TZ0.b","subjectId":"43-dp-biology-last-assessment-2024","title":"Explain the changes in ventilation after 35 seconds.","paper":"3","level":"SL","questionNumber":"b","marksAvailable":"[Maximum mark: 2]","breadcrumbLabels":["Core","Core","Topic 6: Human physiology","6.4 Gas exchange","Core","Topic 6: Human physiology"],"memberSectionIds":[],"sectionOrders":{}}}