{"questionId":"9081307","questionHtml":"<div class=\"qb-parent-stem\"><p>The diagram (not to scale) represents the average brain volume of six species of mammal. The mammals are arranged in rank order of body mass.</p>\n<p style=\"text-align:center;\"><img src=\"__IMG__/81d1de88a17bd6f6d09fc73570d3b935e8db84fb.png\"></p></div>\n<div class=\"qb-leaf-prompt\"><p>State <strong>one</strong> function of each of the following areas of the brain.</p>\n<p>Broca’s area</p></div>","markschemeHtml":"<p style=\"text-align:left;\">speech production/language processing&nbsp;✔</p>","meta":{"questionId":"9081307","referenceCode":"18N.3.HL.TZ0.c.i","subjectId":"43-dp-biology-last-assessment-2024","title":"State one function of each of the following areas of the brain. Broca’s area","paper":"3","level":"HL","questionNumber":"c.i","marksAvailable":"[Maximum mark: 1]","breadcrumbLabels":["Option A: Neurobiology and behaviour","Option A: Neurobiology and behaviour","Option A: Neurobiology and behaviour (Core topics)","A.2 The human brain","Option A: Neurobiology and behaviour","Option A: Neurobiology and behaviour (Core topics)"],"memberSectionIds":[],"sectionOrders":{}},"schemaVersion":2}