{"questionId":"9148","questionHtml":"<p>What observation did William Harvey use as evidence for the circulation of blood?</p>\n<p>A. The ventricles of the heart pump blood out into arteries.</p>\n<p>B. Valves ensure unidirectional flow of blood.</p>\n<p>C. Capillaries carry blood from arteries to veins.</p>\n<p>D. All organs of the body have a separate blood supply.</p>","markschemeHtml":"<p>B</p>","meta":{"questionId":"9148","referenceCode":"19M.1.HL.TZ2.30","subjectId":"43-dp-biology-last-assessment-2024","title":"What observation did William Harvey use as evidence for the circulation of blood? A. The ventricles of the heart pump blood out into arteries. B. Valves ensure unidirectional flow ","paper":"1","level":"HL","questionNumber":"30","marksAvailable":"[Maximum mark: 1]","breadcrumbLabels":["Core","Core","Topic 6: Human physiology","6.2 The blood system","Core","Topic 6: Human physiology"],"memberSectionIds":[],"sectionOrders":{}}}