{"questionId":"11921","questionHtml":"<p>Hence determine, with a reason, if the survey is reliable.</p>","markschemeHtml":"<p>Since the value of <span class=\"mjpage\"><math xmlns=\"http://www.w3.org/1998/Math/MathML\" alttext=\"r\">\n  <mi>r</mi>\n</math></span> is close to +1,&nbsp;<strong>&nbsp;</strong><em><strong>&nbsp; &nbsp; &nbsp; &nbsp; &nbsp;R1</strong></em></p>\n<p>The survey is reliable.&nbsp; <em><strong>&nbsp; &nbsp; &nbsp; &nbsp; &nbsp;A1</strong></em></p>\n<p><em><strong>[2 marks]</strong></em></p>","meta":{"questionId":"11921","referenceCode":"EXM.1.AHL.TZ0.19d","subjectId":"51-dp-mathematics-applications-and-interpretation","title":"Hence determine, with a reason, if the survey is reliable.","paper":"1","level":"AHL","questionNumber":"d","marksAvailable":"[Maximum mark: 2]","breadcrumbLabels":["Topic 4—Statistics and probability","Topic 4—Statistics and probability","AHL 4.12—Data collection, reliability and validity tests"],"memberSectionIds":[],"sectionOrders":{}}}