{"questionId":"12326","questionHtml":"<div class=\"qb-parent-stem\"><p>The heights, <span class=\"mjpage\"><math xmlns=\"http://www.w3.org/1998/Math/MathML\" alttext=\"x\">\n  <mi>x</mi>\n</math></span> metres, of the 241 new entrants to a men’s college were measured and the following statistics calculated.</p>\n<p><span class=\"mjpage mjpage__block\"><math xmlns=\"http://www.w3.org/1998/Math/MathML\" display=\"block\" alttext=\"\\sum {x = 412.11,\\,\\,\\sum {{x^2} = 705.5721} } \">\n  <mo>∑</mo>\n  <mrow>\n    <mi>x</mi>\n    <mo>=</mo>\n    <mn>412.11</mn>\n    <mo>,</mo>\n    <mspace width=\"thinmathspace\"></mspace>\n    <mspace width=\"thinmathspace\"></mspace>\n    <mo>∑</mo>\n    <mrow>\n      <mrow>\n        <msup>\n          <mi>x</mi>\n          <mn>2</mn>\n        </msup>\n      </mrow>\n      <mo>=</mo>\n      <mn>705.5721</mn>\n    </mrow>\n  </mrow>\n</math></span></p></div>\n<div class=\"qb-parent-stem\"><p>The Head of Mathematics decided to use a <span class=\"mjpage\"><math xmlns=\"http://www.w3.org/1998/Math/MathML\" alttext=\"{\\chi ^2}\">\n  <mrow>\n    <msup>\n      <mi>χ</mi>\n      <mn>2</mn>\n    </msup>\n  </mrow>\n</math></span>&nbsp;test to determine whether or not these heights could be modelled by a normal distribution. He therefore divided the data into classes as follows.</p>\n<p style=\"text-align:center;\"><img src=\"__IMG__/1dc93991ab55ed3e5d53de64e2088df17f16087b.png\"></p></div>\n<div class=\"qb-leaf-prompt\"><p class=\"indent2\">Calculate the value of the <span class=\"mjpage\"><math alttext=\"{\\chi ^2}\" xmlns=\"http://www.w3.org/1998/Math/MathML\"> <mrow> <msup> <mi>χ</mi> <mn>2</mn> </msup> </mrow> </math></span>&nbsp;statistic and state your conclusion using a 10% level of significance.</p></div>","markschemeHtml":"<p>The expected frequencies are</p>\n<p><img src=\"__IMG__/05f27ce7de58f19bb60e8531ed753a02ddafee70.png\">&nbsp; &nbsp; &nbsp; &nbsp;<em><strong>A1</strong></em><em><strong>A1</strong></em><em><strong>A1</strong></em><em><strong>A1</strong></em><em><strong>A1</strong></em><em><strong>A1</strong></em></p>\n<p><span class=\"mjpage\"><math alttext=\"{\\chi ^2} = \\frac{{{5^2}}}{{8.04}} + \\frac{{{{34}^2}}}{{30.19}} +&nbsp; \\ldots&nbsp; + \\frac{{{{12}^2}}}{{16.10}} - 241 = 3.30\\,{\\text{/}}\\,3.29\" xmlns=\"http://www.w3.org/1998/Math/MathML\"> <mrow> <msup> <mi>χ</mi> <mn>2</mn> </msup> </mrow> <mo>=</mo> <mfrac> <mrow> <mrow> <msup> <mn>5</mn> <mn>2</mn> </msup> </mrow> </mrow> <mrow> <mn>8.04</mn> </mrow> </mfrac> <mo>+</mo> <mfrac> <mrow> <mrow> <msup> <mrow> <mn>34</mn> </mrow> <mn>2</mn> </msup> </mrow> </mrow> <mrow> <mn>30.19</mn> </mrow> </mfrac> <mo>+</mo> <mo>…</mo> <mo>+</mo> <mfrac> <mrow> <mrow> <msup> <mrow> <mn>12</mn> </mrow> <mn>2</mn> </msup> </mrow> </mrow> <mrow> <mn>16.10</mn> </mrow> </mfrac> <mo>−</mo> <mn>241</mn> <mo>=</mo> <mn>3.30</mn> <mspace width=\"thinmathspace\"></mspace> <mrow> <mtext>/</mtext> </mrow> <mspace width=\"thinmathspace\"></mspace> <mn>3.29</mn> </math></span>&nbsp; &nbsp; &nbsp; &nbsp;<em><strong>M1</strong></em><em><strong>A1</strong></em></p>\n<p>Degrees of freedom = 3&nbsp; &nbsp; &nbsp; &nbsp;<em><strong>A1</strong></em></p>\n<p>Critical value = 6.251 or <em>p</em>-value = 0.35&nbsp; &nbsp; &nbsp; &nbsp;<em><strong>A1</strong></em></p>\n<p>The data can be modelled by a normal distribution.&nbsp; &nbsp; &nbsp; &nbsp;<em><strong>R1</strong></em></p>\n<p><em><strong>[11 marks]</strong></em></p>","meta":{"questionId":"12326","referenceCode":"EXM.1.AHL.TZ0.59b.ii","subjectId":"51-dp-mathematics-applications-and-interpretation","title":"Calculate the value of the χ 2 statistic and state your conclusion using a 10% level of significance.","paper":"1","level":"HL","questionNumber":"b.ii","marksAvailable":"[Maximum mark: 11]","breadcrumbLabels":["Topic 4—Statistics and probability","Topic 4—Statistics and probability","SL 4.9—Normal distribution and calculations","Topic 4—Statistics and probability","SL 4.11—Expected, observed, hypotheses, chi squared, gof, t-test","Topic 4—Statistics and probability","AHL 4.12—Data collection, reliability and validity tests","Topic 4—Statistics and probability","AHL 4.14—Linear transformation of a single RV, E(X) and VAR(X), unbiased estimators"],"memberSectionIds":[],"sectionOrders":{}},"schemaVersion":2}