{"questionId":"17592","questionHtml":"<p>the <math xmlns=\"http://www.w3.org/1998/Math/MathML\"><mi>p</mi></math>-value.</p>","markschemeHtml":"<p>(<math xmlns=\"http://www.w3.org/1998/Math/MathML\"><mi>p</mi></math>-value <math xmlns=\"http://www.w3.org/1998/Math/MathML\"><mo>=</mo></math>)&nbsp; <math xmlns=\"http://www.w3.org/1998/Math/MathML\"><mn>0</mn><mo>.</mo><mn>265</mn><mo>&nbsp;</mo><mfenced><mrow><mn>0</mn><mo>.</mo><mn>264803</mn><mo>…</mo></mrow></mfenced></math>&nbsp; &nbsp; &nbsp;&nbsp;<em><strong>(G1)</strong></em></p>\n<p><strong>Note:</strong> Award <em><strong>(G0)(G2)</strong></em> if the&nbsp;<math xmlns=\"http://www.w3.org/1998/Math/MathML\"><msup><mi>χ</mi><mn>2</mn></msup></math> statistic is missing or incorrect and the <math xmlns=\"http://www.w3.org/1998/Math/MathML\"><mi>p</mi></math>-value is correct.</p>\n<p><em><strong>[1 mark]</strong></em></p>","meta":{"questionId":"17592","referenceCode":"19N.2.SL.TZ0.T_1d.ii","subjectId":"51-dp-mathematics-applications-and-interpretation","title":"the p-value.","paper":"2","level":"SL","questionNumber":"d.ii","marksAvailable":"[Maximum mark: 1]","breadcrumbLabels":["Topic 4—Statistics and probability","Topic 4—Statistics and probability","SL 4.2—Histograms, CF graphs, box plots","Topic 4—Statistics and probability","SL 4.5—Probability concepts, expected numbers","Topic 4—Statistics and probability","SL 4.6—Combined, mutually exclusive, conditional, independence, prob diagrams","Topic 4—Statistics and probability","SL 4.11—Expected, observed, hypotheses, chi squared, gof, t-test"],"memberSectionIds":[],"sectionOrders":{}}}