{"questionId":"21645","questionHtml":"<div class=\"qb-parent-stem\"><p>Charlotte decides to model the shape of a cupcake to calculate its volume.</p>\n<p><img style=\"display:block;margin-left:auto;margin-right:auto;\" src=\"__IMG__/4245581b17486dca580f995d41ea866bd7ac7821.png\"></p>\n<p>From rotating a photograph of her cupcake she estimates that its cross-section passes&nbsp;through the points <math xmlns=\"http://www.w3.org/1998/Math/MathML\"><mo>(</mo><mn>0</mn><mo>,</mo><mo>&nbsp;</mo><mn>3</mn><mo>.</mo><mn>5</mn><mo>)</mo><mo>,</mo><mo>&nbsp;</mo><mo>(</mo><mn>4</mn><mo>,</mo><mo>&nbsp;</mo><mn>6</mn><mo>)</mo><mo>,</mo><mo>&nbsp;</mo><mo>(</mo><mn>6</mn><mo>.</mo><mn>5</mn><mo>,</mo><mo>&nbsp;</mo><mn>4</mn><mo>)</mo><mo>,</mo><mo>&nbsp;</mo><mo>(</mo><mn>7</mn><mo>,</mo><mo>&nbsp;</mo><mn>3</mn><mo>)</mo></math> and&nbsp;<math xmlns=\"http://www.w3.org/1998/Math/MathML\"><mo>(</mo><mn>7</mn><mo>.</mo><mn>5</mn><mo>,</mo><mo>&nbsp;</mo><mn>0</mn><mo>)</mo></math>, where all units are in&nbsp;centimetres. The cross-section is symmetrical in the <math xmlns=\"http://www.w3.org/1998/Math/MathML\"><mi>x</mi></math>-axis, as shown below:</p>\n<p><img style=\"display:block;margin-left:auto;margin-right:auto;\" src=\"__IMG__/76ffc5e524ee327e6a1ca2525800669c038d0e0b.png\"></p>\n<p>She models the section from <math xmlns=\"http://www.w3.org/1998/Math/MathML\"><mo>(</mo><mn>0</mn><mo>,</mo><mo>&nbsp;</mo><mn>3</mn><mo>.</mo><mn>5</mn><mo>)</mo></math> to <math xmlns=\"http://www.w3.org/1998/Math/MathML\"><mo>(</mo><mn>4</mn><mo>,</mo><mo>&nbsp;</mo><mn>6</mn><mo>)</mo></math> as a straight line.</p></div>\n<div class=\"qb-parent-stem\"><p>Charlotte models the section of the cupcake that passes through the points <math xmlns=\"http://www.w3.org/1998/Math/MathML\"><mo>(</mo><mn>4</mn><mo>,</mo><mo>&nbsp;</mo><mn>6</mn><mo>)</mo><mo>,</mo><mo>&nbsp;</mo><mo>(</mo><mn>6</mn><mo>.</mo><mn>5</mn><mo>,</mo><mo>&nbsp;</mo><mn>4</mn><mo>)</mo><mo>,</mo><mo>&nbsp;</mo><mo>(</mo><mn>7</mn><mo>,</mo><mo>&nbsp;</mo><mn>3</mn><mo>)</mo></math> and&nbsp;<math xmlns=\"http://www.w3.org/1998/Math/MathML\"><mo>(</mo><mn>7</mn><mo>.</mo><mn>5</mn><mo>,</mo><mo>&nbsp;</mo><mn>0</mn><mo>)</mo></math> with a quadratic curve.</p></div>\n<div class=\"qb-parent-stem\"><p>Charlotte thinks that a quadratic with a maximum point at <math xmlns=\"http://www.w3.org/1998/Math/MathML\"><mo>(</mo><mn>4</mn><mo>,</mo><mo>&nbsp;</mo><mn>6</mn><mo>)</mo></math> and that passes through&nbsp;the point <math xmlns=\"http://www.w3.org/1998/Math/MathML\"><mo>(</mo><mn>7</mn><mo>.</mo><mn>5</mn><mo>,</mo><mo>&nbsp;</mo><mn>0</mn><mo>)</mo></math> would be a better fit.</p></div>\n<div class=\"qb-parent-stem\"><p>Believing this to be a better model for her cupcake, Charlotte finds the volume of revolution&nbsp;about the <math xmlns=\"http://www.w3.org/1998/Math/MathML\"><mi>x</mi></math>-axis to estimate the volume of the cupcake.</p></div>\n<div class=\"qb-leaf-prompt\"><p>Write down an expression for her estimate of the volume as a sum of two integrals.</p></div>","markschemeHtml":"<p><math xmlns=\"http://www.w3.org/1998/Math/MathML\"><mi mathvariant=\"normal\">π</mi><msubsup><mo>∫</mo><mn>0</mn><mn>4</mn></msubsup><msup><mfenced><mrow><mfrac><mn>5</mn><mn>8</mn></mfrac><mi>x</mi><mo>+</mo><mn>3</mn><mo>.</mo><mn>5</mn></mrow></mfenced><mn>2</mn></msup><mo>d</mo><mi>x</mi><mo>+</mo><mi mathvariant=\"normal\">π</mi><msubsup><mo>∫</mo><mn>4</mn><mrow><mn>7</mn><mo>.</mo><mn>5</mn></mrow></msubsup><msup><mfenced><mrow><mo>-</mo><mfrac><mn>24</mn><mn>49</mn></mfrac><msup><mfenced><mrow><mi>x</mi><mo>-</mo><mn>4</mn></mrow></mfenced><mn>2</mn></msup><mo>+</mo><mn>6</mn></mrow></mfenced><mn>2</mn></msup><mo>d</mo><mi>x</mi></math>&nbsp; &nbsp; &nbsp; &nbsp; &nbsp; &nbsp; &nbsp; &nbsp; &nbsp; &nbsp; &nbsp; &nbsp;<em><strong>(M1)(M1)&nbsp;(M1)A1</strong></em></p>\n<p><br><strong>Note:</strong> Award <em><strong>(M1)(M1)(M1)A0</strong></em> if <math xmlns=\"http://www.w3.org/1998/Math/MathML\"><mi mathvariant=\"normal\">π</mi></math> is omitted but response is otherwise correct. Award <em><strong>(M1)</strong></em> for an integral that indicates volume,<em><strong> (M1)</strong></em> for their part (a) within their volume integral, <em><strong>(M1)</strong></em> for their part (b)(i) within their volume integral, <em><strong>A1</strong></em> for their correct two integrals with all correct limits.</p>\n<p>&nbsp;</p>\n<p><em><strong>[4 marks]</strong></em></p>","meta":{"questionId":"21645","referenceCode":"21M.2.AHL.TZ1.4d.i","subjectId":"51-dp-mathematics-applications-and-interpretation","title":"Write down an expression for her estimate of the volume as a sum of two integrals.","paper":"2","level":"HL","questionNumber":"d.i","marksAvailable":"[Maximum mark: 4]","breadcrumbLabels":["Topic 5—Calculus","Topic 5—Calculus","AHL 5.12—Areas under a curve onto x or y axis. Volumes of revolution about x and y"],"memberSectionIds":[],"sectionOrders":{}},"schemaVersion":2}