{"questionId":"22071","questionHtml":"<p>Write down expressions for <math xmlns=\"http://www.w3.org/1998/Math/MathML\"><msub><mi>M</mi><mrow><mi>n</mi><mo>+</mo><mn>1</mn></mrow></msub></math> and <math xmlns=\"http://www.w3.org/1998/Math/MathML\"><msub><mi>S</mi><mrow><mi>n</mi><mo>+</mo><mn>1</mn></mrow></msub></math> in terms of <math xmlns=\"http://www.w3.org/1998/Math/MathML\"><msub><mi>M</mi><mi>n</mi></msub></math> and <math xmlns=\"http://www.w3.org/1998/Math/MathML\"><msub><mi>S</mi><mi>n</mi></msub></math>.</p>","markschemeHtml":"<p>an attempt to set up one recursive equation&nbsp; &nbsp; &nbsp; &nbsp; &nbsp; &nbsp; &nbsp; &nbsp;&nbsp;<em><strong>(M1)</strong></em></p>\n<p><br><strong>Note:</strong> Must include <strong>two</strong> given parameters <strong>and</strong> <math xmlns=\"http://www.w3.org/1998/Math/MathML\"><msub><mi>M</mi><mi>n</mi></msub></math>&nbsp;and <math xmlns=\"http://www.w3.org/1998/Math/MathML\"><msub><mi>S</mi><mi>n</mi></msub></math> <strong>and</strong> <math xmlns=\"http://www.w3.org/1998/Math/MathML\"><msub><mi>M</mi><mrow><mi>n</mi><mo>+</mo><mn>1</mn></mrow></msub></math>&nbsp;or <math xmlns=\"http://www.w3.org/1998/Math/MathML\"><msub><mi>S</mi><mrow><mi>n</mi><mo>+</mo><mn>1</mn></mrow></msub></math> for the <em><strong>(M1)</strong></em> to be awarded.</p>\n<p><br><math xmlns=\"http://www.w3.org/1998/Math/MathML\"><msub><mi>M</mi><mrow><mi>n</mi><mo>+</mo><mn>1</mn></mrow></msub><mo>=</mo><msub><mi>M</mi><mi>n</mi></msub><mo>+</mo><mn>0</mn><mo>.</mo><mn>1</mn><mfenced><mrow><mn>0</mn><mo>.</mo><mn>549</mn><msub><mi>M</mi><mi>n</mi></msub><mo>-</mo><mn>0</mn><mo>.</mo><mn>236</mn><msub><mi>M</mi><mi>n</mi></msub><msub><mi>S</mi><mi>n</mi></msub></mrow></mfenced></math>&nbsp;&nbsp; &nbsp; &nbsp; &nbsp; &nbsp; &nbsp; &nbsp; &nbsp;&nbsp;<em><strong>A1</strong></em></p>\n<p><math xmlns=\"http://www.w3.org/1998/Math/MathML\"><msub><mi>S</mi><mrow><mi>n</mi><mo>+</mo><mn>1</mn></mrow></msub><mo>=</mo><msub><mi>S</mi><mi>n</mi></msub><mo>+</mo><mn>0</mn><mo>.</mo><mn>1</mn><mfenced><mrow><mn>0</mn><mo>.</mo><mn>244</mn><msub><mi>M</mi><mi>n</mi></msub><msub><mi>S</mi><mi>n</mi></msub><mo>-</mo><mn>1</mn><mo>.</mo><mn>39</mn><msub><mi>S</mi><mi>n</mi></msub></mrow></mfenced></math>&nbsp;&nbsp; &nbsp; &nbsp; &nbsp; &nbsp; &nbsp; &nbsp; &nbsp;&nbsp;<em><strong>A1</strong></em></p>\n<p>&nbsp;</p>\n<p><em><strong>[3 marks]</strong></em></p>","meta":{"questionId":"22071","referenceCode":"21M.3.AHL.TZ2.2e.i","subjectId":"51-dp-mathematics-applications-and-interpretation","title":"Write down expressions for Mn+1 and Sn+1 in terms of Mn and Sn.","paper":"3","level":"AHL","questionNumber":"e.i","marksAvailable":"[Maximum mark: 3]","breadcrumbLabels":["Topic 5—Calculus","Topic 5—Calculus","AHL 5.16—Eulers method for 1st order DEs"],"memberSectionIds":[],"sectionOrders":{}}}