{"questionId":"26822","questionHtml":"<p>Find the total cost for Eddie’s order.</p>","markschemeHtml":"<p><math xmlns=\"http://www.w3.org/1998/Math/MathML\"><mn>35</mn><mo>+</mo><mfenced><mrow><mn>32</mn><mo>×</mo><mn>2</mn><mo>.</mo><mn>45</mn></mrow></mfenced></math>&nbsp; &nbsp; &nbsp; &nbsp; &nbsp;&nbsp;<em><strong>(M1)</strong></em></p>\n<p><math xmlns=\"http://www.w3.org/1998/Math/MathML\"><mo>$</mo><mn>113</mn><mo>&nbsp;</mo><mo>&nbsp;</mo><mfenced><mrow><mn>113</mn><mo>.</mo><mn>4</mn></mrow></mfenced></math>&nbsp;&nbsp; &nbsp; &nbsp; &nbsp;&nbsp;<em><strong>A1</strong></em></p>\n<p>&nbsp;</p>\n<p><em><strong>[2 marks]</strong></em></p>","meta":{"questionId":"26822","referenceCode":"22M.2.SL.TZ1.2g","subjectId":"51-dp-mathematics-applications-and-interpretation","title":"Find the total cost for Eddie’s order.","paper":"2","level":"SL","questionNumber":"g","marksAvailable":"[Maximum mark: 2]","breadcrumbLabels":["Prior learning"],"memberSectionIds":[],"sectionOrders":{}}}