{"questionId":"27837","questionHtml":"<p>Find how many times brighter Acubens is compared to Ceres.</p>","markschemeHtml":"<p><math xmlns=\"http://www.w3.org/1998/Math/MathML\"><mfrac><mrow><mn>0</mn><mo>.</mo><mn>0525</mn></mrow><mrow><mn>0</mn><mo>.</mo><mn>00398107</mn></mrow></mfrac></math>&nbsp;&nbsp; &nbsp; &nbsp; &nbsp; &nbsp; &nbsp; &nbsp; &nbsp; &nbsp; &nbsp; &nbsp; &nbsp; &nbsp; &nbsp;<em><strong>(M1)</strong></em></p>\n<p><math xmlns=\"http://www.w3.org/1998/Math/MathML\"><mo>=</mo><mn>13</mn><mo>.</mo><mn>2</mn><mo>&nbsp;</mo><mo>&nbsp;</mo><mfenced><mrow><mn>13</mn><mo>.</mo><mn>1874</mn><mo>…</mo></mrow></mfenced></math>&nbsp;&nbsp; &nbsp; &nbsp; &nbsp; &nbsp; &nbsp; &nbsp; &nbsp; &nbsp; &nbsp; &nbsp; &nbsp; &nbsp; &nbsp;<em><strong>A1</strong></em></p>\n<p>&nbsp;</p>\n<p><em><strong>[2 marks]</strong></em></p>","meta":{"questionId":"27837","referenceCode":"22N.1.SL.TZ0.10c","subjectId":"51-dp-mathematics-applications-and-interpretation","title":"Find how many times brighter Acubens is compared to Ceres.","paper":"1","level":"SL","questionNumber":"c","marksAvailable":"[Maximum mark: 2]","breadcrumbLabels":["Topic 1—Number and algebra","Topic 2—Functions","Topic 2—Functions","SL 2.6—Modelling skills","Topic 1—Number and algebra","SL 1.5—Intro to logs"],"memberSectionIds":[],"sectionOrders":{}}}