{"questionId":"28021","questionHtml":"<p>the <math xmlns=\"http://www.w3.org/1998/Math/MathML\"><mi>p</mi></math>-value;</p>","markschemeHtml":"<p><math xmlns=\"http://www.w3.org/1998/Math/MathML\"><mi>p</mi></math>-value<math xmlns=\"http://www.w3.org/1998/Math/MathML\"><mo> </mo><mo>=</mo><mn>0</mn><mo>.</mo><mn>954</mn><mo>&nbsp;</mo><mo>&nbsp;</mo><mfenced><mrow><mn>0</mn><mo>.</mo><mn>953872</mn><mo>…</mo></mrow></mfenced></math>&nbsp;&nbsp; &nbsp; &nbsp; &nbsp; &nbsp; &nbsp; &nbsp; &nbsp; &nbsp; &nbsp; &nbsp; &nbsp;&nbsp;<em><strong>(M1)A1</strong></em></p>\n<p>&nbsp;</p>\n<p><em><strong>[2 marks]</strong></em></p>","meta":{"questionId":"28021","referenceCode":"22N.3.AHL.TZ0.1d.iii","subjectId":"51-dp-mathematics-applications-and-interpretation","title":"the p-value;","paper":"3","level":"AHL","questionNumber":"d.iii","marksAvailable":"[Maximum mark: 2]","breadcrumbLabels":["Topic 4—Statistics and probability","Topic 4—Statistics and probability","SL 4.11—Expected, observed, hypotheses, chi squared, gof, t-test"],"memberSectionIds":[],"sectionOrders":{}}}