{"questionId":"35036193","questionHtml":"<p>The cloth used to make Nanako’s bag costs 4 Japanese Yen (JPY) per cm<sup>2</sup>.</p>\n<p>Find the cost of the cloth used to make Nanako’s bag.</p>","markschemeHtml":"<p><span class=\"mjpage\"><math xmlns=\"http://www.w3.org/1998/Math/MathML\" alttext=\"\\left( {3{{\\left( {12} \\right)}^2} + \\frac{{10368}}{{12}}} \\right) \\times 4\">\n  <mrow>\n    <mo>(</mo>\n    <mrow>\n      <mn>3</mn>\n      <mrow>\n        <msup>\n          <mrow>\n            <mrow>\n              <mo>(</mo>\n              <mrow>\n                <mn>12</mn>\n              </mrow>\n              <mo>)</mo>\n            </mrow>\n          </mrow>\n          <mn>2</mn>\n        </msup>\n      </mrow>\n      <mo>+</mo>\n      <mfrac>\n        <mrow>\n          <mn>10368</mn>\n        </mrow>\n        <mrow>\n          <mn>12</mn>\n        </mrow>\n      </mfrac>\n    </mrow>\n    <mo>)</mo>\n  </mrow>\n  <mo>×</mo>\n  <mn>4</mn>\n</math></span>&nbsp;&nbsp; &nbsp; &nbsp;&nbsp;<em><strong>(M1)</strong></em></p>\n<p>&nbsp;</p>\n<p><strong>Note:</strong> Award <em><strong>(M1)</strong></em> for substituting 12 into the area formula and for multiplying the area formula by 4.</p>\n<p>&nbsp;</p>\n<p>= 5180 (JPY)&nbsp; &nbsp; (5184 (JPY))&nbsp; &nbsp; &nbsp;&nbsp;<em><strong>(A1)(G2)</strong></em></p>\n<p>&nbsp;</p>\n<p><em><strong>[2 marks]</strong></em></p>","meta":{"questionId":"35036193","referenceCode":"18N.2.SL.TZ0.T_6h","subjectId":"51-dp-mathematics-applications-and-interpretation","title":"The cloth used to make Nanako’s bag costs 4 Japanese Yen (JPY) per cm2. Find the cost of the cloth used to make Nanako’s bag.","paper":"2","level":"SL","questionNumber":"h","marksAvailable":"[Maximum mark: 2]","breadcrumbLabels":["Topic 5—Calculus","Topic 5—Calculus","SL 5.1—Introduction of differential calculus","Topic 5—Calculus","SL 5.3—Differentiating polynomials, n E Z","Topic 5—Calculus","SL 5.6—Stationary points, local max and min","Topic 5—Calculus","SL 5.7—Optimisation"],"memberSectionIds":[],"sectionOrders":{}}}